CHANGES.txt
LICENSE.txt
MANIFEST.in
README.rst
requirements.txt
setup.py
memsql_collectd/__init__.py
memsql_collectd/analytics.py
memsql_collectd/cluster.py
memsql_collectd/plugin.py
memsql_collectd/util.py
memsql_collectd.egg-info/PKG-INFO
memsql_collectd.egg-info/SOURCES.txt
memsql_collectd.egg-info/dependency_links.txt
memsql_collectd.egg-info/not-zip-safe
memsql_collectd.egg-info/requires.txt
memsql_collectd.egg-info/top_level.txt