Metadata-Version: 1.1
Name: memsql-collectd
Version: 0.0.1
Summary: The official MemSQL collectd plugin.
Home-page: http://github.com/memsql/memsql-collectd
Author: MemSQL
Author-email: support@memsql.com
License: LICENSE.txt
Platform: UNKNOWN
Classifier: License :: OSI Approved :: MIT License
Classifier: Programming Language :: Python :: 2.6
Classifier: Programming Language :: Python :: 2.7
